gymbullet_diffbotenv/__init__.py
gymbullet_diffbotenv/envs/GymBullet_DiffBot.py
gymbullet_diffbotenv/envs/__init__.py
GymBullet_DiffBotEnv-0.1.4.dist-info/METADATA
GymBullet_DiffBotEnv-0.1.4.dist-info/WHEEL
GymBullet_DiffBotEnv-0.1.4.dist-info/top_level.txt
GymBullet_DiffBotEnv-0.1.4.dist-info/RECORD
