Metadata-Version: 2.1
Name: GymBullet-DiffBotEnv
Version: 0.1.4
Summary: A OpenAI Gym Environment for Pybullet DiffBot Package
Home-page: UNKNOWN
License: UNKNOWN
Platform: UNKNOWN
Requires-Dist: gym
Requires-Dist: numpy
Requires-Dist: pybullet
